[
  {
    "timestamp": "2026-05-23T00:45:30Z",
    "run_id": "26318823946",
    "results": [
      {
        "name": "CHA",
        "success": true,
        "http_code": 200,
        "message": "Login erfolgreich \u2013 https://www.vierlande-food.de/b2bsalesrepresentative",
        "timestamp": "2026-05-23T00:45:20Z"
      },
      {
        "name": "SAP",
        "success": true,
        "http_code": 200,
        "message": "Login erfolgreich \u2013 https://www.frisch-frost.de/b2bsalesrepresentative",
        "timestamp": "2026-05-23T00:45:25Z"
      }
    ]
  },
  {
    "timestamp": "2026-05-23T00:30:35Z",
    "run_id": "26318456155",
    "results": [
      {
        "name": "CHA",
        "success": true,
        "http_code": 200,
        "message": "Login erfolgreich \u2013 https://www.vierlande-food.de/b2bsalesrepresentative",
        "timestamp": "2026-05-23T00:30:26Z"
      },
      {
        "name": "SAP",
        "success": true,
        "http_code": 200,
        "message": "Login erfolgreich \u2013 https://www.frisch-frost.de/b2bsalesrepresentative",
        "timestamp": "2026-05-23T00:30:30Z"
      }
    ]
  },
  {
    "timestamp": "2026-05-23T00:15:27Z",
    "run_id": "26318087611",
    "results": [
      {
        "name": "CHA",
        "success": true,
        "http_code": 200,
        "message": "Login erfolgreich \u2013 https://www.vierlande-food.de/b2bsalesrepresentative",
        "timestamp": "2026-05-23T00:15:18Z"
      },
      {
        "name": "SAP",
        "success": true,
        "http_code": 200,
        "message": "Login erfolgreich \u2013 https://www.frisch-frost.de/b2bsalesrepresentative",
        "timestamp": "2026-05-23T00:15:22Z"
      }
    ]
  },
  {
    "timestamp": "2026-05-23T00:00:45Z",
    "run_id": "26317709152",
    "results": [
      {
        "name": "CHA",
        "success": true,
        "http_code": 200,
        "message": "Login erfolgreich \u2013 https://www.vierlande-food.de/b2bsalesrepresentative",
        "timestamp": "2026-05-23T00:00:35Z"
      },
      {
        "name": "SAP",
        "success": true,
        "http_code": 200,
        "message": "Login erfolgreich \u2013 https://www.frisch-frost.de/b2bsalesrepresentative",
        "timestamp": "2026-05-23T00:00:40Z"
      }
    ]
  },
  {
    "timestamp": "2026-05-22T23:45:29Z",
    "run_id": "26317305000",
    "results": [
      {
        "name": "CHA",
        "success": true,
        "http_code": 200,
        "message": "Login erfolgreich \u2013 https://www.vierlande-food.de/b2bsalesrepresentative",
        "timestamp": "2026-05-22T23:45:21Z"
      },
      {
        "name": "SAP",
        "success": true,
        "http_code": 200,
        "message": "Login erfolgreich \u2013 https://www.frisch-frost.de/b2bsalesrepresentative",
        "timestamp": "2026-05-22T23:45:25Z"
      }
    ]
  },
  {
    "timestamp": "2026-05-22T23:30:38Z",
    "run_id": "26316890507",
    "results": [
      {
        "name": "CHA",
        "success": true,
        "http_code": 200,
        "message": "Login erfolgreich \u2013 https://www.vierlande-food.de/b2bsalesrepresentative",
        "timestamp": "2026-05-22T23:30:28Z"
      },
      {
        "name": "SAP",
        "success": true,
        "http_code": 200,
        "message": "Login erfolgreich \u2013 https://www.frisch-frost.de/b2bsalesrepresentative",
        "timestamp": "2026-05-22T23:30:33Z"
      }
    ]
  },
  {
    "timestamp": "2026-05-22T23:15:35Z",
    "run_id": "26316469916",
    "results": [
      {
        "name": "CHA",
        "success": true,
        "http_code": 200,
        "message": "Login erfolgreich \u2013 https://www.vierlande-food.de/b2bsalesrepresentative",
        "timestamp": "2026-05-22T23:15:25Z"
      },
      {
        "name": "SAP",
        "success": true,
        "http_code": 200,
        "message": "Login erfolgreich \u2013 https://www.frisch-frost.de/b2bsalesrepresentative",
        "timestamp": "2026-05-22T23:15:30Z"
      }
    ]
  },
  {
    "timestamp": "2026-05-22T23:00:40Z",
    "run_id": "26316040184",
    "results": [
      {
        "name": "CHA",
        "success": true,
        "http_code": 200,
        "message": "Login erfolgreich \u2013 https://www.vierlande-food.de/b2bsalesrepresentative",
        "timestamp": "2026-05-22T23:00:32Z"
      },
      {
        "name": "SAP",
        "success": true,
        "http_code": 200,
        "message": "Login erfolgreich \u2013 https://www.frisch-frost.de/b2bsalesrepresentative",
        "timestamp": "2026-05-22T23:00:36Z"
      }
    ]
  },
  {
    "timestamp": "2026-05-22T22:45:25Z",
    "run_id": "26315567715",
    "results": [
      {
        "name": "CHA",
        "success": true,
        "http_code": 200,
        "message": "Login erfolgreich \u2013 https://www.vierlande-food.de/b2bsalesrepresentative",
        "timestamp": "2026-05-22T22:45:16Z"
      },
      {
        "name": "SAP",
        "success": true,
        "http_code": 200,
        "message": "Login erfolgreich \u2013 https://www.frisch-frost.de/b2bsalesrepresentative",
        "timestamp": "2026-05-22T22:45:21Z"
      }
    ]
  },
  {
    "timestamp": "2026-05-22T22:30:34Z",
    "run_id": "26315082654",
    "results": [
      {
        "name": "CHA",
        "success": true,
        "http_code": 200,
        "message": "Login erfolgreich \u2013 https://www.vierlande-food.de/b2bsalesrepresentative",
        "timestamp": "2026-05-22T22:30:25Z"
      },
      {
        "name": "SAP",
        "success": true,
        "http_code": 200,
        "message": "Login erfolgreich \u2013 https://www.frisch-frost.de/b2bsalesrepresentative",
        "timestamp": "2026-05-22T22:30:30Z"
      }
    ]
  },
  {
    "timestamp": "2026-05-22T22:15:32Z",
    "run_id": "26314579628",
    "results": [
      {
        "name": "CHA",
        "success": true,
        "http_code": 200,
        "message": "Login erfolgreich \u2013 https://www.vierlande-food.de/b2bsalesrepresentative",
        "timestamp": "2026-05-22T22:15:22Z"
      },
      {
        "name": "SAP",
        "success": true,
        "http_code": 200,
        "message": "Login erfolgreich \u2013 https://www.frisch-frost.de/b2bsalesrepresentative",
        "timestamp": "2026-05-22T22:15:27Z"
      }
    ]
  },
  {
    "timestamp": "2026-05-22T22:00:42Z",
    "run_id": "26314058856",
    "results": [
      {
        "name": "CHA",
        "success": true,
        "http_code": 200,
        "message": "Login erfolgreich \u2013 https://www.vierlande-food.de/b2bsalesrepresentative",
        "timestamp": "2026-05-22T22:00:32Z"
      },
      {
        "name": "SAP",
        "success": true,
        "http_code": 200,
        "message": "Login erfolgreich \u2013 https://www.frisch-frost.de/b2bsalesrepresentative",
        "timestamp": "2026-05-22T22:00:37Z"
      }
    ]
  },
  {
    "timestamp": "2026-05-22T21:45:30Z",
    "run_id": "26313502278",
    "results": [
      {
        "name": "CHA",
        "success": true,
        "http_code": 200,
        "message": "Login erfolgreich \u2013 https://www.vierlande-food.de/b2bsalesrepresentative",
        "timestamp": "2026-05-22T21:45:21Z"
      },
      {
        "name": "SAP",
        "success": true,
        "http_code": 200,
        "message": "Login erfolgreich \u2013 https://www.frisch-frost.de/b2bsalesrepresentative",
        "timestamp": "2026-05-22T21:45:25Z"
      }
    ]
  },
  {
    "timestamp": "2026-05-22T21:30:41Z",
    "run_id": "26312924814",
    "results": [
      {
        "name": "CHA",
        "success": true,
        "http_code": 200,
        "message": "Login erfolgreich \u2013 https://www.vierlande-food.de/b2bsalesrepresentative",
        "timestamp": "2026-05-22T21:30:33Z"
      },
      {
        "name": "SAP",
        "success": true,
        "http_code": 200,
        "message": "Login erfolgreich \u2013 https://www.frisch-frost.de/b2bsalesrepresentative",
        "timestamp": "2026-05-22T21:30:37Z"
      }
    ]
  },
  {
    "timestamp": "2026-05-22T21:15:27Z",
    "run_id": "26312321112",
    "results": [
      {
        "name": "CHA",
        "success": true,
        "http_code": 200,
        "message": "Login erfolgreich \u2013 https://www.vierlande-food.de/b2bsalesrepresentative",
        "timestamp": "2026-05-22T21:15:17Z"
      },
      {
        "name": "SAP",
        "success": true,
        "http_code": 200,
        "message": "Login erfolgreich \u2013 https://www.frisch-frost.de/b2bsalesrepresentative",
        "timestamp": "2026-05-22T21:15:22Z"
      }
    ]
  },
  {
    "timestamp": "2026-05-22T21:00:45Z",
    "run_id": "26311735658",
    "results": [
      {
        "name": "CHA",
        "success": true,
        "http_code": 200,
        "message": "Login erfolgreich \u2013 https://www.vierlande-food.de/b2bsalesrepresentative",
        "timestamp": "2026-05-22T21:00:36Z"
      },
      {
        "name": "SAP",
        "success": true,
        "http_code": 200,
        "message": "Login erfolgreich \u2013 https://www.frisch-frost.de/b2bsalesrepresentative",
        "timestamp": "2026-05-22T21:00:40Z"
      }
    ]
  },
  {
    "timestamp": "2026-05-22T20:45:27Z",
    "run_id": "26311099391",
    "results": [
      {
        "name": "CHA",
        "success": true,
        "http_code": 200,
        "message": "Login erfolgreich \u2013 https://www.vierlande-food.de/b2bsalesrepresentative",
        "timestamp": "2026-05-22T20:45:19Z"
      },
      {
        "name": "SAP",
        "success": true,
        "http_code": 200,
        "message": "Login erfolgreich \u2013 https://www.frisch-frost.de/b2bsalesrepresentative",
        "timestamp": "2026-05-22T20:45:23Z"
      }
    ]
  },
  {
    "timestamp": "2026-05-22T20:30:34Z",
    "run_id": "26310466411",
    "results": [
      {
        "name": "CHA",
        "success": true,
        "http_code": 200,
        "message": "Login erfolgreich \u2013 https://www.vierlande-food.de/b2bsalesrepresentative",
        "timestamp": "2026-05-22T20:30:25Z"
      },
      {
        "name": "SAP",
        "success": true,
        "http_code": 200,
        "message": "Login erfolgreich \u2013 https://www.frisch-frost.de/b2bsalesrepresentative",
        "timestamp": "2026-05-22T20:30:29Z"
      }
    ]
  },
  {
    "timestamp": "2026-05-22T20:15:28Z",
    "run_id": "26309826529",
    "results": [
      {
        "name": "CHA",
        "success": true,
        "http_code": 200,
        "message": "Login erfolgreich \u2013 https://www.vierlande-food.de/b2bsalesrepresentative",
        "timestamp": "2026-05-22T20:15:18Z"
      },
      {
        "name": "SAP",
        "success": true,
        "http_code": 200,
        "message": "Login erfolgreich \u2013 https://www.frisch-frost.de/b2bsalesrepresentative",
        "timestamp": "2026-05-22T20:15:23Z"
      }
    ]
  },
  {
    "timestamp": "2026-05-22T20:00:41Z",
    "run_id": "26309195978",
    "results": [
      {
        "name": "CHA",
        "success": true,
        "http_code": 200,
        "message": "Login erfolgreich \u2013 https://www.vierlande-food.de/b2bsalesrepresentative",
        "timestamp": "2026-05-22T20:00:33Z"
      },
      {
        "name": "SAP",
        "success": true,
        "http_code": 200,
        "message": "Login erfolgreich \u2013 https://www.frisch-frost.de/b2bsalesrepresentative",
        "timestamp": "2026-05-22T20:00:37Z"
      }
    ]
  },
  {
    "timestamp": "2026-05-22T19:45:29Z",
    "run_id": "26308523400",
    "results": [
      {
        "name": "CHA",
        "success": true,
        "http_code": 200,
        "message": "Login erfolgreich \u2013 https://www.vierlande-food.de/b2bsalesrepresentative",
        "timestamp": "2026-05-22T19:45:21Z"
      },
      {
        "name": "SAP",
        "success": true,
        "http_code": 200,
        "message": "Login erfolgreich \u2013 https://www.frisch-frost.de/b2bsalesrepresentative",
        "timestamp": "2026-05-22T19:45:25Z"
      }
    ]
  },
  {
    "timestamp": "2026-05-22T19:30:32Z",
    "run_id": "26307859599",
    "results": [
      {
        "name": "CHA",
        "success": true,
        "http_code": 200,
        "message": "Login erfolgreich \u2013 https://www.vierlande-food.de/b2bsalesrepresentative",
        "timestamp": "2026-05-22T19:30:23Z"
      },
      {
        "name": "SAP",
        "success": true,
        "http_code": 200,
        "message": "Login erfolgreich \u2013 https://www.frisch-frost.de/b2bsalesrepresentative",
        "timestamp": "2026-05-22T19:30:28Z"
      }
    ]
  },
  {
    "timestamp": "2026-05-22T19:15:38Z",
    "run_id": "26307185251",
    "results": [
      {
        "name": "CHA",
        "success": true,
        "http_code": 200,
        "message": "Login erfolgreich \u2013 https://www.vierlande-food.de/b2bsalesrepresentative",
        "timestamp": "2026-05-22T19:15:27Z"
      },
      {
        "name": "SAP",
        "success": true,
        "http_code": 200,
        "message": "Login erfolgreich \u2013 https://www.frisch-frost.de/b2bsalesrepresentative",
        "timestamp": "2026-05-22T19:15:32Z"
      }
    ]
  },
  {
    "timestamp": "2026-05-22T19:00:46Z",
    "run_id": "26306505636",
    "results": [
      {
        "name": "CHA",
        "success": true,
        "http_code": 200,
        "message": "Login erfolgreich \u2013 https://www.vierlande-food.de/b2bsalesrepresentative",
        "timestamp": "2026-05-22T19:00:36Z"
      },
      {
        "name": "SAP",
        "success": true,
        "http_code": 200,
        "message": "Login erfolgreich \u2013 https://www.frisch-frost.de/b2bsalesrepresentative",
        "timestamp": "2026-05-22T19:00:41Z"
      }
    ]
  },
  {
    "timestamp": "2026-05-22T18:45:26Z",
    "run_id": "26305804236",
    "results": [
      {
        "name": "CHA",
        "success": true,
        "http_code": 200,
        "message": "Login erfolgreich \u2013 https://www.vierlande-food.de/b2bsalesrepresentative",
        "timestamp": "2026-05-22T18:45:18Z"
      },
      {
        "name": "SAP",
        "success": true,
        "http_code": 200,
        "message": "Login erfolgreich \u2013 https://www.frisch-frost.de/b2bsalesrepresentative",
        "timestamp": "2026-05-22T18:45:22Z"
      }
    ]
  },
  {
    "timestamp": "2026-05-22T18:30:34Z",
    "run_id": "26305161116",
    "results": [
      {
        "name": "CHA",
        "success": true,
        "http_code": 200,
        "message": "Login erfolgreich \u2013 https://www.vierlande-food.de/b2bsalesrepresentative",
        "timestamp": "2026-05-22T18:30:26Z"
      },
      {
        "name": "SAP",
        "success": true,
        "http_code": 200,
        "message": "Login erfolgreich \u2013 https://www.frisch-frost.de/b2bsalesrepresentative",
        "timestamp": "2026-05-22T18:30:30Z"
      }
    ]
  },
  {
    "timestamp": "2026-05-22T18:15:25Z",
    "run_id": "26304503971",
    "results": [
      {
        "name": "CHA",
        "success": true,
        "http_code": 200,
        "message": "Login erfolgreich \u2013 https://www.vierlande-food.de/b2bsalesrepresentative",
        "timestamp": "2026-05-22T18:15:17Z"
      },
      {
        "name": "SAP",
        "success": true,
        "http_code": 200,
        "message": "Login erfolgreich \u2013 https://www.frisch-frost.de/b2bsalesrepresentative",
        "timestamp": "2026-05-22T18:15:21Z"
      }
    ]
  },
  {
    "timestamp": "2026-05-22T18:00:42Z",
    "run_id": "26303832589",
    "results": [
      {
        "name": "CHA",
        "success": true,
        "http_code": 200,
        "message": "Login erfolgreich \u2013 https://www.vierlande-food.de/b2bsalesrepresentative",
        "timestamp": "2026-05-22T18:00:33Z"
      },
      {
        "name": "SAP",
        "success": true,
        "http_code": 200,
        "message": "Login erfolgreich \u2013 https://www.frisch-frost.de/b2bsalesrepresentative",
        "timestamp": "2026-05-22T18:00:37Z"
      }
    ]
  },
  {
    "timestamp": "2026-05-22T17:45:29Z",
    "run_id": "26303136520",
    "results": [
      {
        "name": "CHA",
        "success": true,
        "http_code": 200,
        "message": "Login erfolgreich \u2013 https://www.vierlande-food.de/b2bsalesrepresentative",
        "timestamp": "2026-05-22T17:45:19Z"
      },
      {
        "name": "SAP",
        "success": true,
        "http_code": 200,
        "message": "Login erfolgreich \u2013 https://www.frisch-frost.de/b2bsalesrepresentative",
        "timestamp": "2026-05-22T17:45:24Z"
      }
    ]
  },
  {
    "timestamp": "2026-05-22T17:30:39Z",
    "run_id": "26302457412",
    "results": [
      {
        "name": "CHA",
        "success": true,
        "http_code": 200,
        "message": "Login erfolgreich \u2013 https://www.vierlande-food.de/b2bsalesrepresentative",
        "timestamp": "2026-05-22T17:30:28Z"
      },
      {
        "name": "SAP",
        "success": true,
        "http_code": 200,
        "message": "Login erfolgreich \u2013 https://www.frisch-frost.de/b2bsalesrepresentative",
        "timestamp": "2026-05-22T17:30:33Z"
      }
    ]
  },
  {
    "timestamp": "2026-05-22T17:15:27Z",
    "run_id": "26301771218",
    "results": [
      {
        "name": "CHA",
        "success": true,
        "http_code": 200,
        "message": "Login erfolgreich \u2013 https://www.vierlande-food.de/b2bsalesrepresentative",
        "timestamp": "2026-05-22T17:15:19Z"
      },
      {
        "name": "SAP",
        "success": true,
        "http_code": 200,
        "message": "Login erfolgreich \u2013 https://www.frisch-frost.de/b2bsalesrepresentative",
        "timestamp": "2026-05-22T17:15:23Z"
      }
    ]
  },
  {
    "timestamp": "2026-05-22T17:00:50Z",
    "run_id": "26301104503",
    "results": [
      {
        "name": "CHA",
        "success": true,
        "http_code": 200,
        "message": "Login erfolgreich \u2013 https://www.vierlande-food.de/b2bsalesrepresentative",
        "timestamp": "2026-05-22T17:00:40Z"
      },
      {
        "name": "SAP",
        "success": true,
        "http_code": 200,
        "message": "Login erfolgreich \u2013 https://www.frisch-frost.de/b2bsalesrepresentative",
        "timestamp": "2026-05-22T17:00:45Z"
      }
    ]
  },
  {
    "timestamp": "2026-05-22T16:45:33Z",
    "run_id": "26300387347",
    "results": [
      {
        "name": "CHA",
        "success": true,
        "http_code": 200,
        "message": "Login erfolgreich \u2013 https://www.vierlande-food.de/b2bsalesrepresentative",
        "timestamp": "2026-05-22T16:45:24Z"
      },
      {
        "name": "SAP",
        "success": true,
        "http_code": 200,
        "message": "Login erfolgreich \u2013 https://www.frisch-frost.de/b2bsalesrepresentative",
        "timestamp": "2026-05-22T16:45:28Z"
      }
    ]
  },
  {
    "timestamp": "2026-05-22T16:30:34Z",
    "run_id": "26299695153",
    "results": [
      {
        "name": "CHA",
        "success": true,
        "http_code": 200,
        "message": "Login erfolgreich \u2013 https://www.vierlande-food.de/b2bsalesrepresentative",
        "timestamp": "2026-05-22T16:30:25Z"
      },
      {
        "name": "SAP",
        "success": true,
        "http_code": 200,
        "message": "Login erfolgreich \u2013 https://www.frisch-frost.de/b2bsalesrepresentative",
        "timestamp": "2026-05-22T16:30:29Z"
      }
    ]
  },
  {
    "timestamp": "2026-05-22T16:15:31Z",
    "run_id": "26298988936",
    "results": [
      {
        "name": "CHA",
        "success": true,
        "http_code": 200,
        "message": "Login erfolgreich \u2013 https://www.vierlande-food.de/b2bsalesrepresentative",
        "timestamp": "2026-05-22T16:15:21Z"
      },
      {
        "name": "SAP",
        "success": true,
        "http_code": 200,
        "message": "Login erfolgreich \u2013 https://www.frisch-frost.de/b2bsalesrepresentative",
        "timestamp": "2026-05-22T16:15:26Z"
      }
    ]
  },
  {
    "timestamp": "2026-05-22T16:00:43Z",
    "run_id": "26298289535",
    "results": [
      {
        "name": "CHA",
        "success": true,
        "http_code": 200,
        "message": "Login erfolgreich \u2013 https://www.vierlande-food.de/b2bsalesrepresentative",
        "timestamp": "2026-05-22T16:00:34Z"
      },
      {
        "name": "SAP",
        "success": true,
        "http_code": 200,
        "message": "Login erfolgreich \u2013 https://www.frisch-frost.de/b2bsalesrepresentative",
        "timestamp": "2026-05-22T16:00:38Z"
      }
    ]
  },
  {
    "timestamp": "2026-05-22T15:45:28Z",
    "run_id": "26297527543",
    "results": [
      {
        "name": "CHA",
        "success": true,
        "http_code": 200,
        "message": "Login erfolgreich \u2013 https://www.vierlande-food.de/b2bsalesrepresentative",
        "timestamp": "2026-05-22T15:45:19Z"
      },
      {
        "name": "SAP",
        "success": true,
        "http_code": 200,
        "message": "Login erfolgreich \u2013 https://www.frisch-frost.de/b2bsalesrepresentative",
        "timestamp": "2026-05-22T15:45:23Z"
      }
    ]
  },
  {
    "timestamp": "2026-05-22T15:30:37Z",
    "run_id": "26296791481",
    "results": [
      {
        "name": "CHA",
        "success": true,
        "http_code": 200,
        "message": "Login erfolgreich \u2013 https://www.vierlande-food.de/b2bsalesrepresentative",
        "timestamp": "2026-05-22T15:30:29Z"
      },
      {
        "name": "SAP",
        "success": true,
        "http_code": 200,
        "message": "Login erfolgreich \u2013 https://www.frisch-frost.de/b2bsalesrepresentative",
        "timestamp": "2026-05-22T15:30:33Z"
      }
    ]
  },
  {
    "timestamp": "2026-05-22T15:15:29Z",
    "run_id": "26296038184",
    "results": [
      {
        "name": "CHA",
        "success": true,
        "http_code": 200,
        "message": "Login erfolgreich \u2013 https://www.vierlande-food.de/b2bsalesrepresentative",
        "timestamp": "2026-05-22T15:15:20Z"
      },
      {
        "name": "SAP",
        "success": true,
        "http_code": 200,
        "message": "Login erfolgreich \u2013 https://www.frisch-frost.de/b2bsalesrepresentative",
        "timestamp": "2026-05-22T15:15:24Z"
      }
    ]
  },
  {
    "timestamp": "2026-05-22T15:00:47Z",
    "run_id": "26295305347",
    "results": [
      {
        "name": "CHA",
        "success": true,
        "http_code": 200,
        "message": "Login erfolgreich \u2013 https://www.vierlande-food.de/b2bsalesrepresentative",
        "timestamp": "2026-05-22T15:00:38Z"
      },
      {
        "name": "SAP",
        "success": true,
        "http_code": 200,
        "message": "Login erfolgreich \u2013 https://www.frisch-frost.de/b2bsalesrepresentative",
        "timestamp": "2026-05-22T15:00:42Z"
      }
    ]
  },
  {
    "timestamp": "2026-05-22T14:45:29Z",
    "run_id": "26294522837",
    "results": [
      {
        "name": "CHA",
        "success": true,
        "http_code": 200,
        "message": "Login erfolgreich \u2013 https://www.vierlande-food.de/b2bsalesrepresentative",
        "timestamp": "2026-05-22T14:45:20Z"
      },
      {
        "name": "SAP",
        "success": true,
        "http_code": 200,
        "message": "Login erfolgreich \u2013 https://www.frisch-frost.de/b2bsalesrepresentative",
        "timestamp": "2026-05-22T14:45:25Z"
      }
    ]
  },
  {
    "timestamp": "2026-05-22T14:30:37Z",
    "run_id": "26293747939",
    "results": [
      {
        "name": "CHA",
        "success": true,
        "http_code": 200,
        "message": "Login erfolgreich \u2013 https://www.vierlande-food.de/b2bsalesrepresentative",
        "timestamp": "2026-05-22T14:30:29Z"
      },
      {
        "name": "SAP",
        "success": true,
        "http_code": 200,
        "message": "Login erfolgreich \u2013 https://www.frisch-frost.de/b2bsalesrepresentative",
        "timestamp": "2026-05-22T14:30:33Z"
      }
    ]
  },
  {
    "timestamp": "2026-05-22T14:15:39Z",
    "run_id": "26292976096",
    "results": [
      {
        "name": "CHA",
        "success": true,
        "http_code": 200,
        "message": "Login erfolgreich \u2013 https://www.vierlande-food.de/b2bsalesrepresentative",
        "timestamp": "2026-05-22T14:15:29Z"
      },
      {
        "name": "SAP",
        "success": true,
        "http_code": 200,
        "message": "Login erfolgreich \u2013 https://www.frisch-frost.de/b2bsalesrepresentative",
        "timestamp": "2026-05-22T14:15:34Z"
      }
    ]
  },
  {
    "timestamp": "2026-05-22T14:00:43Z",
    "run_id": "26292236097",
    "results": [
      {
        "name": "CHA",
        "success": true,
        "http_code": 200,
        "message": "Login erfolgreich \u2013 https://www.vierlande-food.de/b2bsalesrepresentative",
        "timestamp": "2026-05-22T14:00:34Z"
      },
      {
        "name": "SAP",
        "success": true,
        "http_code": 200,
        "message": "Login erfolgreich \u2013 https://www.frisch-frost.de/b2bsalesrepresentative",
        "timestamp": "2026-05-22T14:00:38Z"
      }
    ]
  },
  {
    "timestamp": "2026-05-22T13:45:33Z",
    "run_id": "26291454583",
    "results": [
      {
        "name": "CHA",
        "success": true,
        "http_code": 200,
        "message": "Login erfolgreich \u2013 https://www.vierlande-food.de/b2bsalesrepresentative",
        "timestamp": "2026-05-22T13:45:22Z"
      },
      {
        "name": "SAP",
        "success": true,
        "http_code": 200,
        "message": "Login erfolgreich \u2013 https://www.frisch-frost.de/b2bsalesrepresentative",
        "timestamp": "2026-05-22T13:45:27Z"
      }
    ]
  },
  {
    "timestamp": "2026-05-22T13:30:38Z",
    "run_id": "26290707559",
    "results": [
      {
        "name": "CHA",
        "success": true,
        "http_code": 200,
        "message": "Login erfolgreich \u2013 https://www.vierlande-food.de/b2bsalesrepresentative",
        "timestamp": "2026-05-22T13:30:29Z"
      },
      {
        "name": "SAP",
        "success": true,
        "http_code": 200,
        "message": "Login erfolgreich \u2013 https://www.frisch-frost.de/b2bsalesrepresentative",
        "timestamp": "2026-05-22T13:30:33Z"
      }
    ]
  },
  {
    "timestamp": "2026-05-22T13:15:32Z",
    "run_id": "26289966918",
    "results": [
      {
        "name": "CHA",
        "success": true,
        "http_code": 200,
        "message": "Login erfolgreich \u2013 https://www.vierlande-food.de/b2bsalesrepresentative",
        "timestamp": "2026-05-22T13:15:21Z"
      },
      {
        "name": "SAP",
        "success": true,
        "http_code": 200,
        "message": "Login erfolgreich \u2013 https://www.frisch-frost.de/b2bsalesrepresentative",
        "timestamp": "2026-05-22T13:15:27Z"
      }
    ]
  },
  {
    "timestamp": "2026-05-22T13:00:43Z",
    "run_id": "26289261061",
    "results": [
      {
        "name": "CHA",
        "success": true,
        "http_code": 200,
        "message": "Login erfolgreich \u2013 https://www.vierlande-food.de/b2bsalesrepresentative",
        "timestamp": "2026-05-22T13:00:35Z"
      },
      {
        "name": "SAP",
        "success": true,
        "http_code": 200,
        "message": "Login erfolgreich \u2013 https://www.frisch-frost.de/b2bsalesrepresentative",
        "timestamp": "2026-05-22T13:00:39Z"
      }
    ]
  },
  {
    "timestamp": "2026-05-22T12:45:29Z",
    "run_id": "26288536369",
    "results": [
      {
        "name": "CHA",
        "success": true,
        "http_code": 200,
        "message": "Login erfolgreich \u2013 https://www.vierlande-food.de/b2bsalesrepresentative",
        "timestamp": "2026-05-22T12:45:21Z"
      },
      {
        "name": "SAP",
        "success": true,
        "http_code": 200,
        "message": "Login erfolgreich \u2013 https://www.frisch-frost.de/b2bsalesrepresentative",
        "timestamp": "2026-05-22T12:45:25Z"
      }
    ]
  },
  {
    "timestamp": "2026-05-22T12:30:38Z",
    "run_id": "26287853306",
    "results": [
      {
        "name": "CHA",
        "success": true,
        "http_code": 200,
        "message": "Login erfolgreich \u2013 https://www.vierlande-food.de/b2bsalesrepresentative",
        "timestamp": "2026-05-22T12:30:29Z"
      },
      {
        "name": "SAP",
        "success": true,
        "http_code": 200,
        "message": "Login erfolgreich \u2013 https://www.frisch-frost.de/b2bsalesrepresentative",
        "timestamp": "2026-05-22T12:30:33Z"
      }
    ]
  },
  {
    "timestamp": "2026-05-22T12:15:28Z",
    "run_id": "26287172136",
    "results": [
      {
        "name": "CHA",
        "success": true,
        "http_code": 200,
        "message": "Login erfolgreich \u2013 https://www.vierlande-food.de/b2bsalesrepresentative",
        "timestamp": "2026-05-22T12:15:19Z"
      },
      {
        "name": "SAP",
        "success": true,
        "http_code": 200,
        "message": "Login erfolgreich \u2013 https://www.frisch-frost.de/b2bsalesrepresentative",
        "timestamp": "2026-05-22T12:15:23Z"
      }
    ]
  },
  {
    "timestamp": "2026-05-22T12:00:47Z",
    "run_id": "26286527758",
    "results": [
      {
        "name": "CHA",
        "success": true,
        "http_code": 200,
        "message": "Login erfolgreich \u2013 https://www.vierlande-food.de/b2bsalesrepresentative",
        "timestamp": "2026-05-22T12:00:36Z"
      },
      {
        "name": "SAP",
        "success": true,
        "http_code": 200,
        "message": "Login erfolgreich \u2013 https://www.frisch-frost.de/b2bsalesrepresentative",
        "timestamp": "2026-05-22T12:00:42Z"
      }
    ]
  },
  {
    "timestamp": "2026-05-22T11:45:31Z",
    "run_id": "26285862731",
    "results": [
      {
        "name": "CHA",
        "success": true,
        "http_code": 200,
        "message": "Login erfolgreich \u2013 https://www.vierlande-food.de/b2bsalesrepresentative",
        "timestamp": "2026-05-22T11:45:21Z"
      },
      {
        "name": "SAP",
        "success": true,
        "http_code": 200,
        "message": "Login erfolgreich \u2013 https://www.frisch-frost.de/b2bsalesrepresentative",
        "timestamp": "2026-05-22T11:45:26Z"
      }
    ]
  },
  {
    "timestamp": "2026-05-22T11:30:33Z",
    "run_id": "26285223822",
    "results": [
      {
        "name": "CHA",
        "success": true,
        "http_code": 200,
        "message": "Login erfolgreich \u2013 https://www.vierlande-food.de/b2bsalesrepresentative",
        "timestamp": "2026-05-22T11:30:24Z"
      },
      {
        "name": "SAP",
        "success": true,
        "http_code": 200,
        "message": "Login erfolgreich \u2013 https://www.frisch-frost.de/b2bsalesrepresentative",
        "timestamp": "2026-05-22T11:30:28Z"
      }
    ]
  },
  {
    "timestamp": "2026-05-22T11:15:26Z",
    "run_id": "26284570694",
    "results": [
      {
        "name": "CHA",
        "success": true,
        "http_code": 200,
        "message": "Login erfolgreich \u2013 https://www.vierlande-food.de/b2bsalesrepresentative",
        "timestamp": "2026-05-22T11:15:17Z"
      },
      {
        "name": "SAP",
        "success": true,
        "http_code": 200,
        "message": "Login erfolgreich \u2013 https://www.frisch-frost.de/b2bsalesrepresentative",
        "timestamp": "2026-05-22T11:15:22Z"
      }
    ]
  },
  {
    "timestamp": "2026-05-22T11:00:41Z",
    "run_id": "26283932751",
    "results": [
      {
        "name": "CHA",
        "success": true,
        "http_code": 200,
        "message": "Login erfolgreich \u2013 https://www.vierlande-food.de/b2bsalesrepresentative",
        "timestamp": "2026-05-22T11:00:32Z"
      },
      {
        "name": "SAP",
        "success": true,
        "http_code": 200,
        "message": "Login erfolgreich \u2013 https://www.frisch-frost.de/b2bsalesrepresentative",
        "timestamp": "2026-05-22T11:00:36Z"
      }
    ]
  },
  {
    "timestamp": "2026-05-22T10:45:28Z",
    "run_id": "26283260988",
    "results": [
      {
        "name": "CHA",
        "success": true,
        "http_code": 200,
        "message": "Login erfolgreich \u2013 https://www.vierlande-food.de/b2bsalesrepresentative",
        "timestamp": "2026-05-22T10:45:19Z"
      },
      {
        "name": "SAP",
        "success": true,
        "http_code": 200,
        "message": "Login erfolgreich \u2013 https://www.frisch-frost.de/b2bsalesrepresentative",
        "timestamp": "2026-05-22T10:45:23Z"
      }
    ]
  },
  {
    "timestamp": "2026-05-22T10:30:41Z",
    "run_id": "26282610363",
    "results": [
      {
        "name": "CHA",
        "success": true,
        "http_code": 200,
        "message": "Login erfolgreich \u2013 https://www.vierlande-food.de/b2bsalesrepresentative",
        "timestamp": "2026-05-22T10:30:30Z"
      },
      {
        "name": "SAP",
        "success": true,
        "http_code": 200,
        "message": "Login erfolgreich \u2013 https://www.frisch-frost.de/b2bsalesrepresentative",
        "timestamp": "2026-05-22T10:30:36Z"
      }
    ]
  },
  {
    "timestamp": "2026-05-22T10:15:29Z",
    "run_id": "26281955866",
    "results": [
      {
        "name": "CHA",
        "success": true,
        "http_code": 200,
        "message": "Login erfolgreich \u2013 https://www.vierlande-food.de/b2bsalesrepresentative",
        "timestamp": "2026-05-22T10:15:19Z"
      },
      {
        "name": "SAP",
        "success": true,
        "http_code": 200,
        "message": "Login erfolgreich \u2013 https://www.frisch-frost.de/b2bsalesrepresentative",
        "timestamp": "2026-05-22T10:15:24Z"
      }
    ]
  },
  {
    "timestamp": "2026-05-22T10:00:42Z",
    "run_id": "26281308182",
    "results": [
      {
        "name": "CHA",
        "success": true,
        "http_code": 200,
        "message": "Login erfolgreich \u2013 https://www.vierlande-food.de/b2bsalesrepresentative",
        "timestamp": "2026-05-22T10:00:33Z"
      },
      {
        "name": "SAP",
        "success": true,
        "http_code": 200,
        "message": "Login erfolgreich \u2013 https://www.frisch-frost.de/b2bsalesrepresentative",
        "timestamp": "2026-05-22T10:00:37Z"
      }
    ]
  },
  {
    "timestamp": "2026-05-22T09:45:29Z",
    "run_id": "26280613213",
    "results": [
      {
        "name": "CHA",
        "success": true,
        "http_code": 200,
        "message": "Login erfolgreich \u2013 https://www.vierlande-food.de/b2bsalesrepresentative",
        "timestamp": "2026-05-22T09:45:19Z"
      },
      {
        "name": "SAP",
        "success": true,
        "http_code": 200,
        "message": "Login erfolgreich \u2013 https://www.frisch-frost.de/b2bsalesrepresentative",
        "timestamp": "2026-05-22T09:45:24Z"
      }
    ]
  },
  {
    "timestamp": "2026-05-22T09:30:36Z",
    "run_id": "26279944690",
    "results": [
      {
        "name": "CHA",
        "success": true,
        "http_code": 200,
        "message": "Login erfolgreich \u2013 https://www.vierlande-food.de/b2bsalesrepresentative",
        "timestamp": "2026-05-22T09:30:27Z"
      },
      {
        "name": "SAP",
        "success": true,
        "http_code": 200,
        "message": "Login erfolgreich \u2013 https://www.frisch-frost.de/b2bsalesrepresentative",
        "timestamp": "2026-05-22T09:30:31Z"
      }
    ]
  },
  {
    "timestamp": "2026-05-22T09:15:28Z",
    "run_id": "26279242237",
    "results": [
      {
        "name": "CHA",
        "success": true,
        "http_code": 200,
        "message": "Login erfolgreich \u2013 https://www.vierlande-food.de/b2bsalesrepresentative",
        "timestamp": "2026-05-22T09:15:19Z"
      },
      {
        "name": "SAP",
        "success": true,
        "http_code": 200,
        "message": "Login erfolgreich \u2013 https://www.frisch-frost.de/b2bsalesrepresentative",
        "timestamp": "2026-05-22T09:15:23Z"
      }
    ]
  },
  {
    "timestamp": "2026-05-22T09:00:43Z",
    "run_id": "26278574280",
    "results": [
      {
        "name": "CHA",
        "success": true,
        "http_code": 200,
        "message": "Login erfolgreich \u2013 https://www.vierlande-food.de/b2bsalesrepresentative",
        "timestamp": "2026-05-22T09:00:34Z"
      },
      {
        "name": "SAP",
        "success": true,
        "http_code": 200,
        "message": "Login erfolgreich \u2013 https://www.frisch-frost.de/b2bsalesrepresentative",
        "timestamp": "2026-05-22T09:00:39Z"
      }
    ]
  },
  {
    "timestamp": "2026-05-22T08:45:34Z",
    "run_id": "26277874098",
    "results": [
      {
        "name": "CHA",
        "success": true,
        "http_code": 200,
        "message": "Login erfolgreich \u2013 https://www.vierlande-food.de/b2bsalesrepresentative",
        "timestamp": "2026-05-22T08:45:24Z"
      },
      {
        "name": "SAP",
        "success": true,
        "http_code": 200,
        "message": "Login erfolgreich \u2013 https://www.frisch-frost.de/b2bsalesrepresentative",
        "timestamp": "2026-05-22T08:45:29Z"
      }
    ]
  },
  {
    "timestamp": "2026-05-22T08:30:37Z",
    "run_id": "26277219030",
    "results": [
      {
        "name": "CHA",
        "success": true,
        "http_code": 200,
        "message": "Login erfolgreich \u2013 https://www.vierlande-food.de/b2bsalesrepresentative",
        "timestamp": "2026-05-22T08:30:28Z"
      },
      {
        "name": "SAP",
        "success": true,
        "http_code": 200,
        "message": "Login erfolgreich \u2013 https://www.frisch-frost.de/b2bsalesrepresentative",
        "timestamp": "2026-05-22T08:30:33Z"
      }
    ]
  },
  {
    "timestamp": "2026-05-22T08:15:32Z",
    "run_id": "26276553557",
    "results": [
      {
        "name": "CHA",
        "success": true,
        "http_code": 200,
        "message": "Login erfolgreich \u2013 https://www.vierlande-food.de/b2bsalesrepresentative",
        "timestamp": "2026-05-22T08:15:22Z"
      },
      {
        "name": "SAP",
        "success": true,
        "http_code": 200,
        "message": "Login erfolgreich \u2013 https://www.frisch-frost.de/b2bsalesrepresentative",
        "timestamp": "2026-05-22T08:15:27Z"
      }
    ]
  },
  {
    "timestamp": "2026-05-22T08:00:48Z",
    "run_id": "26275915895",
    "results": [
      {
        "name": "CHA",
        "success": true,
        "http_code": 200,
        "message": "Login erfolgreich \u2013 https://www.vierlande-food.de/b2bsalesrepresentative",
        "timestamp": "2026-05-22T08:00:38Z"
      },
      {
        "name": "SAP",
        "success": true,
        "http_code": 200,
        "message": "Login erfolgreich \u2013 https://www.frisch-frost.de/b2bsalesrepresentative",
        "timestamp": "2026-05-22T08:00:43Z"
      }
    ]
  },
  {
    "timestamp": "2026-05-22T07:45:26Z",
    "run_id": "26275260347",
    "results": [
      {
        "name": "CHA",
        "success": true,
        "http_code": 200,
        "message": "Login erfolgreich \u2013 https://www.vierlande-food.de/b2bsalesrepresentative",
        "timestamp": "2026-05-22T07:45:18Z"
      },
      {
        "name": "SAP",
        "success": true,
        "http_code": 200,
        "message": "Login erfolgreich \u2013 https://www.frisch-frost.de/b2bsalesrepresentative",
        "timestamp": "2026-05-22T07:45:22Z"
      }
    ]
  },
  {
    "timestamp": "2026-05-22T07:30:35Z",
    "run_id": "26274616664",
    "results": [
      {
        "name": "CHA",
        "success": true,
        "http_code": 200,
        "message": "Login erfolgreich \u2013 https://www.vierlande-food.de/b2bsalesrepresentative",
        "timestamp": "2026-05-22T07:30:25Z"
      },
      {
        "name": "SAP",
        "success": true,
        "http_code": 200,
        "message": "Login erfolgreich \u2013 https://www.frisch-frost.de/b2bsalesrepresentative",
        "timestamp": "2026-05-22T07:30:29Z"
      }
    ]
  },
  {
    "timestamp": "2026-05-22T07:15:30Z",
    "run_id": "26273986805",
    "results": [
      {
        "name": "CHA",
        "success": true,
        "http_code": 200,
        "message": "Login erfolgreich \u2013 https://www.vierlande-food.de/b2bsalesrepresentative",
        "timestamp": "2026-05-22T07:15:20Z"
      },
      {
        "name": "SAP",
        "success": true,
        "http_code": 200,
        "message": "Login erfolgreich \u2013 https://www.frisch-frost.de/b2bsalesrepresentative",
        "timestamp": "2026-05-22T07:15:25Z"
      }
    ]
  },
  {
    "timestamp": "2026-05-22T07:00:47Z",
    "run_id": "26273399995",
    "results": [
      {
        "name": "CHA",
        "success": true,
        "http_code": 200,
        "message": "Login erfolgreich \u2013 https://www.vierlande-food.de/b2bsalesrepresentative",
        "timestamp": "2026-05-22T07:00:37Z"
      },
      {
        "name": "SAP",
        "success": true,
        "http_code": 200,
        "message": "Login erfolgreich \u2013 https://www.frisch-frost.de/b2bsalesrepresentative",
        "timestamp": "2026-05-22T07:00:42Z"
      }
    ]
  },
  {
    "timestamp": "2026-05-22T06:45:30Z",
    "run_id": "26272815644",
    "results": [
      {
        "name": "CHA",
        "success": true,
        "http_code": 200,
        "message": "Login erfolgreich \u2013 https://www.vierlande-food.de/b2bsalesrepresentative",
        "timestamp": "2026-05-22T06:45:19Z"
      },
      {
        "name": "SAP",
        "success": true,
        "http_code": 200,
        "message": "Login erfolgreich \u2013 https://www.frisch-frost.de/b2bsalesrepresentative",
        "timestamp": "2026-05-22T06:45:25Z"
      }
    ]
  },
  {
    "timestamp": "2026-05-22T06:30:38Z",
    "run_id": "26272264452",
    "results": [
      {
        "name": "CHA",
        "success": true,
        "http_code": 200,
        "message": "Login erfolgreich \u2013 https://www.vierlande-food.de/b2bsalesrepresentative",
        "timestamp": "2026-05-22T06:30:28Z"
      },
      {
        "name": "SAP",
        "success": true,
        "http_code": 200,
        "message": "Login erfolgreich \u2013 https://www.frisch-frost.de/b2bsalesrepresentative",
        "timestamp": "2026-05-22T06:30:33Z"
      }
    ]
  },
  {
    "timestamp": "2026-05-22T06:15:29Z",
    "run_id": "26271739582",
    "results": [
      {
        "name": "CHA",
        "success": true,
        "http_code": 200,
        "message": "Login erfolgreich \u2013 https://www.vierlande-food.de/b2bsalesrepresentative",
        "timestamp": "2026-05-22T06:15:21Z"
      },
      {
        "name": "SAP",
        "success": true,
        "http_code": 200,
        "message": "Login erfolgreich \u2013 https://www.frisch-frost.de/b2bsalesrepresentative",
        "timestamp": "2026-05-22T06:15:25Z"
      }
    ]
  },
  {
    "timestamp": "2026-05-22T06:00:51Z",
    "run_id": "26271248518",
    "results": [
      {
        "name": "CHA",
        "success": true,
        "http_code": 200,
        "message": "Login erfolgreich \u2013 https://www.vierlande-food.de/b2bsalesrepresentative",
        "timestamp": "2026-05-22T06:00:40Z"
      },
      {
        "name": "SAP",
        "success": true,
        "http_code": 200,
        "message": "Login erfolgreich \u2013 https://www.frisch-frost.de/b2bsalesrepresentative",
        "timestamp": "2026-05-22T06:00:45Z"
      }
    ]
  },
  {
    "timestamp": "2026-05-22T05:45:30Z",
    "run_id": "26270745320",
    "results": [
      {
        "name": "CHA",
        "success": true,
        "http_code": 200,
        "message": "Login erfolgreich \u2013 https://www.vierlande-food.de/b2bsalesrepresentative",
        "timestamp": "2026-05-22T05:45:20Z"
      },
      {
        "name": "SAP",
        "success": true,
        "http_code": 200,
        "message": "Login erfolgreich \u2013 https://www.frisch-frost.de/b2bsalesrepresentative",
        "timestamp": "2026-05-22T05:45:25Z"
      }
    ]
  },
  {
    "timestamp": "2026-05-22T05:30:32Z",
    "run_id": "26270249936",
    "results": [
      {
        "name": "CHA",
        "success": true,
        "http_code": 200,
        "message": "Login erfolgreich \u2013 https://www.vierlande-food.de/b2bsalesrepresentative",
        "timestamp": "2026-05-22T05:30:24Z"
      },
      {
        "name": "SAP",
        "success": true,
        "http_code": 200,
        "message": "Login erfolgreich \u2013 https://www.frisch-frost.de/b2bsalesrepresentative",
        "timestamp": "2026-05-22T05:30:28Z"
      }
    ]
  },
  {
    "timestamp": "2026-05-22T05:15:30Z",
    "run_id": "26269784389",
    "results": [
      {
        "name": "CHA",
        "success": true,
        "http_code": 200,
        "message": "Login erfolgreich \u2013 https://www.vierlande-food.de/b2bsalesrepresentative",
        "timestamp": "2026-05-22T05:15:20Z"
      },
      {
        "name": "SAP",
        "success": true,
        "http_code": 200,
        "message": "Login erfolgreich \u2013 https://www.frisch-frost.de/b2bsalesrepresentative",
        "timestamp": "2026-05-22T05:15:24Z"
      }
    ]
  },
  {
    "timestamp": "2026-05-22T05:00:43Z",
    "run_id": "26269364545",
    "results": [
      {
        "name": "CHA",
        "success": true,
        "http_code": 200,
        "message": "Login erfolgreich \u2013 https://www.vierlande-food.de/b2bsalesrepresentative",
        "timestamp": "2026-05-22T05:00:33Z"
      },
      {
        "name": "SAP",
        "success": true,
        "http_code": 200,
        "message": "Login erfolgreich \u2013 https://www.frisch-frost.de/b2bsalesrepresentative",
        "timestamp": "2026-05-22T05:00:38Z"
      }
    ]
  },
  {
    "timestamp": "2026-05-22T04:45:27Z",
    "run_id": "26268914808",
    "results": [
      {
        "name": "CHA",
        "success": true,
        "http_code": 200,
        "message": "Login erfolgreich \u2013 https://www.vierlande-food.de/b2bsalesrepresentative",
        "timestamp": "2026-05-22T04:45:18Z"
      },
      {
        "name": "SAP",
        "success": true,
        "http_code": 200,
        "message": "Login erfolgreich \u2013 https://www.frisch-frost.de/b2bsalesrepresentative",
        "timestamp": "2026-05-22T04:45:22Z"
      }
    ]
  },
  {
    "timestamp": "2026-05-22T04:30:35Z",
    "run_id": "26268481149",
    "results": [
      {
        "name": "CHA",
        "success": true,
        "http_code": 200,
        "message": "Login erfolgreich \u2013 https://www.vierlande-food.de/b2bsalesrepresentative",
        "timestamp": "2026-05-22T04:30:25Z"
      },
      {
        "name": "SAP",
        "success": true,
        "http_code": 200,
        "message": "Login erfolgreich \u2013 https://www.frisch-frost.de/b2bsalesrepresentative",
        "timestamp": "2026-05-22T04:30:30Z"
      }
    ]
  },
  {
    "timestamp": "2026-05-22T04:15:26Z",
    "run_id": "26268056682",
    "results": [
      {
        "name": "CHA",
        "success": true,
        "http_code": 200,
        "message": "Login erfolgreich \u2013 https://www.vierlande-food.de/b2bsalesrepresentative",
        "timestamp": "2026-05-22T04:15:17Z"
      },
      {
        "name": "SAP",
        "success": true,
        "http_code": 200,
        "message": "Login erfolgreich \u2013 https://www.frisch-frost.de/b2bsalesrepresentative",
        "timestamp": "2026-05-22T04:15:21Z"
      }
    ]
  },
  {
    "timestamp": "2026-05-22T04:00:39Z",
    "run_id": "26267659001",
    "results": [
      {
        "name": "CHA",
        "success": true,
        "http_code": 200,
        "message": "Login erfolgreich \u2013 https://www.vierlande-food.de/b2bsalesrepresentative",
        "timestamp": "2026-05-22T04:00:30Z"
      },
      {
        "name": "SAP",
        "success": true,
        "http_code": 200,
        "message": "Login erfolgreich \u2013 https://www.frisch-frost.de/b2bsalesrepresentative",
        "timestamp": "2026-05-22T04:00:34Z"
      }
    ]
  },
  {
    "timestamp": "2026-05-22T03:45:25Z",
    "run_id": "26267227278",
    "results": [
      {
        "name": "CHA",
        "success": true,
        "http_code": 200,
        "message": "Login erfolgreich \u2013 https://www.vierlande-food.de/b2bsalesrepresentative",
        "timestamp": "2026-05-22T03:45:16Z"
      },
      {
        "name": "SAP",
        "success": true,
        "http_code": 200,
        "message": "Login erfolgreich \u2013 https://www.frisch-frost.de/b2bsalesrepresentative",
        "timestamp": "2026-05-22T03:45:20Z"
      }
    ]
  },
  {
    "timestamp": "2026-05-22T03:30:32Z",
    "run_id": "26266792142",
    "results": [
      {
        "name": "CHA",
        "success": true,
        "http_code": 200,
        "message": "Login erfolgreich \u2013 https://www.vierlande-food.de/b2bsalesrepresentative",
        "timestamp": "2026-05-22T03:30:23Z"
      },
      {
        "name": "SAP",
        "success": true,
        "http_code": 200,
        "message": "Login erfolgreich \u2013 https://www.frisch-frost.de/b2bsalesrepresentative",
        "timestamp": "2026-05-22T03:30:28Z"
      }
    ]
  },
  {
    "timestamp": "2026-05-22T03:15:32Z",
    "run_id": "26266334606",
    "results": [
      {
        "name": "CHA",
        "success": true,
        "http_code": 200,
        "message": "Login erfolgreich \u2013 https://www.vierlande-food.de/b2bsalesrepresentative",
        "timestamp": "2026-05-22T03:15:22Z"
      },
      {
        "name": "SAP",
        "success": true,
        "http_code": 200,
        "message": "Login erfolgreich \u2013 https://www.frisch-frost.de/b2bsalesrepresentative",
        "timestamp": "2026-05-22T03:15:27Z"
      }
    ]
  },
  {
    "timestamp": "2026-05-22T03:00:44Z",
    "run_id": "26265882015",
    "results": [
      {
        "name": "CHA",
        "success": true,
        "http_code": 200,
        "message": "Login erfolgreich \u2013 https://www.vierlande-food.de/b2bsalesrepresentative",
        "timestamp": "2026-05-22T03:00:34Z"
      },
      {
        "name": "SAP",
        "success": true,
        "http_code": 200,
        "message": "Login erfolgreich \u2013 https://www.frisch-frost.de/b2bsalesrepresentative",
        "timestamp": "2026-05-22T03:00:39Z"
      }
    ]
  },
  {
    "timestamp": "2026-05-22T02:45:30Z",
    "run_id": "26265415837",
    "results": [
      {
        "name": "CHA",
        "success": true,
        "http_code": 200,
        "message": "Login erfolgreich \u2013 https://www.vierlande-food.de/b2bsalesrepresentative",
        "timestamp": "2026-05-22T02:45:22Z"
      },
      {
        "name": "SAP",
        "success": true,
        "http_code": 200,
        "message": "Login erfolgreich \u2013 https://www.frisch-frost.de/b2bsalesrepresentative",
        "timestamp": "2026-05-22T02:45:26Z"
      }
    ]
  },
  {
    "timestamp": "2026-05-22T02:30:34Z",
    "run_id": "26264969289",
    "results": [
      {
        "name": "CHA",
        "success": true,
        "http_code": 200,
        "message": "Login erfolgreich \u2013 https://www.vierlande-food.de/b2bsalesrepresentative",
        "timestamp": "2026-05-22T02:30:25Z"
      },
      {
        "name": "SAP",
        "success": true,
        "http_code": 200,
        "message": "Login erfolgreich \u2013 https://www.frisch-frost.de/b2bsalesrepresentative",
        "timestamp": "2026-05-22T02:30:29Z"
      }
    ]
  },
  {
    "timestamp": "2026-05-22T02:15:30Z",
    "run_id": "26264511327",
    "results": [
      {
        "name": "CHA",
        "success": true,
        "http_code": 200,
        "message": "Login erfolgreich \u2013 https://www.vierlande-food.de/b2bsalesrepresentative",
        "timestamp": "2026-05-22T02:15:21Z"
      },
      {
        "name": "SAP",
        "success": true,
        "http_code": 200,
        "message": "Login erfolgreich \u2013 https://www.frisch-frost.de/b2bsalesrepresentative",
        "timestamp": "2026-05-22T02:15:25Z"
      }
    ]
  },
  {
    "timestamp": "2026-05-22T02:00:40Z",
    "run_id": "26264060436",
    "results": [
      {
        "name": "CHA",
        "success": true,
        "http_code": 200,
        "message": "Login erfolgreich \u2013 https://www.vierlande-food.de/b2bsalesrepresentative",
        "timestamp": "2026-05-22T02:00:31Z"
      },
      {
        "name": "SAP",
        "success": true,
        "http_code": 200,
        "message": "Login erfolgreich \u2013 https://www.frisch-frost.de/b2bsalesrepresentative",
        "timestamp": "2026-05-22T02:00:36Z"
      }
    ]
  },
  {
    "timestamp": "2026-05-22T01:45:23Z",
    "run_id": "26263592797",
    "results": [
      {
        "name": "CHA",
        "success": true,
        "http_code": 200,
        "message": "Login erfolgreich \u2013 https://www.vierlande-food.de/b2bsalesrepresentative",
        "timestamp": "2026-05-22T01:45:15Z"
      },
      {
        "name": "SAP",
        "success": true,
        "http_code": 200,
        "message": "Login erfolgreich \u2013 https://www.frisch-frost.de/b2bsalesrepresentative",
        "timestamp": "2026-05-22T01:45:19Z"
      }
    ]
  },
  {
    "timestamp": "2026-05-22T01:30:31Z",
    "run_id": "26263129641",
    "results": [
      {
        "name": "CHA",
        "success": true,
        "http_code": 200,
        "message": "Login erfolgreich \u2013 https://www.vierlande-food.de/b2bsalesrepresentative",
        "timestamp": "2026-05-22T01:30:23Z"
      },
      {
        "name": "SAP",
        "success": true,
        "http_code": 200,
        "message": "Login erfolgreich \u2013 https://www.frisch-frost.de/b2bsalesrepresentative",
        "timestamp": "2026-05-22T01:30:27Z"
      }
    ]
  },
  {
    "timestamp": "2026-05-22T01:15:29Z",
    "run_id": "26262654514",
    "results": [
      {
        "name": "CHA",
        "success": true,
        "http_code": 200,
        "message": "Login erfolgreich \u2013 https://www.vierlande-food.de/b2bsalesrepresentative",
        "timestamp": "2026-05-22T01:15:20Z"
      },
      {
        "name": "SAP",
        "success": true,
        "http_code": 200,
        "message": "Login erfolgreich \u2013 https://www.frisch-frost.de/b2bsalesrepresentative",
        "timestamp": "2026-05-22T01:15:24Z"
      }
    ]
  },
  {
    "timestamp": "2026-05-22T01:00:39Z",
    "run_id": "26262194260",
    "results": [
      {
        "name": "CHA",
        "success": true,
        "http_code": 200,
        "message": "Login erfolgreich \u2013 https://www.vierlande-food.de/b2bsalesrepresentative",
        "timestamp": "2026-05-22T01:00:30Z"
      },
      {
        "name": "SAP",
        "success": true,
        "http_code": 200,
        "message": "Login erfolgreich \u2013 https://www.frisch-frost.de/b2bsalesrepresentative",
        "timestamp": "2026-05-22T01:00:34Z"
      }
    ]
  },
  {
    "timestamp": "2026-05-22T00:45:24Z",
    "run_id": "26261719118",
    "results": [
      {
        "name": "CHA",
        "success": true,
        "http_code": 200,
        "message": "Login erfolgreich \u2013 https://www.vierlande-food.de/b2bsalesrepresentative",
        "timestamp": "2026-05-22T00:45:16Z"
      },
      {
        "name": "SAP",
        "success": true,
        "http_code": 200,
        "message": "Login erfolgreich \u2013 https://www.frisch-frost.de/b2bsalesrepresentative",
        "timestamp": "2026-05-22T00:45:20Z"
      }
    ]
  },
  {
    "timestamp": "2026-05-22T00:30:36Z",
    "run_id": "26261243401",
    "results": [
      {
        "name": "CHA",
        "success": true,
        "http_code": 200,
        "message": "Login erfolgreich \u2013 https://www.vierlande-food.de/b2bsalesrepresentative",
        "timestamp": "2026-05-22T00:30:25Z"
      },
      {
        "name": "SAP",
        "success": true,
        "http_code": 200,
        "message": "Login erfolgreich \u2013 https://www.frisch-frost.de/b2bsalesrepresentative",
        "timestamp": "2026-05-22T00:30:31Z"
      }
    ]
  },
  {
    "timestamp": "2026-05-22T00:15:27Z",
    "run_id": "26260744851",
    "results": [
      {
        "name": "CHA",
        "success": true,
        "http_code": 200,
        "message": "Login erfolgreich \u2013 https://www.vierlande-food.de/b2bsalesrepresentative",
        "timestamp": "2026-05-22T00:15:18Z"
      },
      {
        "name": "SAP",
        "success": true,
        "http_code": 200,
        "message": "Login erfolgreich \u2013 https://www.frisch-frost.de/b2bsalesrepresentative",
        "timestamp": "2026-05-22T00:15:23Z"
      }
    ]
  },
  {
    "timestamp": "2026-05-22T00:00:45Z",
    "run_id": "26260251699",
    "results": [
      {
        "name": "CHA",
        "success": true,
        "http_code": 200,
        "message": "Login erfolgreich \u2013 https://www.vierlande-food.de/b2bsalesrepresentative",
        "timestamp": "2026-05-22T00:00:35Z"
      },
      {
        "name": "SAP",
        "success": true,
        "http_code": 200,
        "message": "Login erfolgreich \u2013 https://www.frisch-frost.de/b2bsalesrepresentative",
        "timestamp": "2026-05-22T00:00:40Z"
      }
    ]
  }
]